mbf_nested_intervals-0.5.0.dist-info/METADATA
mbf_nested_intervals-0.5.0.dist-info/WHEEL
mbf_nested_intervals/__init__.py
mbf_nested_intervals/mbf_nested_intervals.abi3.so
mbf_nested_intervals-0.5.0.dist-info/RECORD
