Metadata-Version: 2.1
Name: mbf_nested_intervals
Version: 0.5.0
Author: Florian Finkernagel <finkernagel@imt.uni-marburg.de>
Author-email: Florian Finkernagel <finkernagel@imt.uni-marburg.de>
